pydocstyle_gitlab_code_quality/__init__.py
pydocstyle_gitlab_code_quality/main.py
pydocstyle_gitlab_code_quality/src/__init__.py
pydocstyle_gitlab_code_quality/src/cq_types.py
pydocstyle_gitlab_code_quality/src/config/__init__.py
pydocstyle_gitlab_code_quality/src/config/cli_parser.py
pydocstyle_gitlab_code_quality/src/config/config.py
pydocstyle_gitlab_code_quality/src/utils/__init__.py
pydocstyle_gitlab_code_quality/src/utils/encoder.py
pydocstyle_gitlab_code_quality/src/utils/logger.py
pydocstyle_gitlab_code_quality-0.1.0.dist-info/LICENSE.md
pydocstyle_gitlab_code_quality-0.1.0.dist-info/METADATA
pydocstyle_gitlab_code_quality-0.1.0.dist-info/WHEEL
pydocstyle_gitlab_code_quality-0.1.0.dist-info/entry_points.txt
pydocstyle_gitlab_code_quality-0.1.0.dist-info/top_level.txt
pydocstyle_gitlab_code_quality-0.1.0.dist-info/RECORD
