Metadata-Version: 2.1
Name: pydocstyle-gitlab-code-quality
Version: 0.1.0
Summary: Simple script to generate gitlab code quality report from output of pydocstyle.
Author-email: Aleksander Kluczka <aleksander.kluczka@gmail.com>
License: MIT
Project-URL: Homepage, https://github.com/vis4rd/pydocstyle-gitlab-code-quality
Project-URL: Bug Tracker, https://github.com/vis4rd/pydocstyle-gitlab-code-quality/issues
Classifier: Development Status :: 3 - Alpha
Classifier: Environment :: Console
Classifier: License :: OSI Approved :: MIT License
Classifier: Operating System :: OS Independent
Classifier: Programming Language :: Python :: 3
Classifier: Programming Language :: Python :: 3.8
Classifier: Programming Language :: Python :: 3.9
Classifier: Programming Language :: Python :: 3.10
Classifier: Programming Language :: Python :: 3.11
Classifier: Programming Language :: Python :: 3.12
Requires-Python: >=3.8
License-File: LICENSE.md
